{
  "English": "Nederlands",
  "dangerous": "gevaarlijk",
  "dead": "dood",
  "hot": "heet",
  "must / have to / should": "moeten",
  "safe": "veilig",
  "the army": "het leger",
  "the attack": "de aanval",
  "the blood": "het bloed",
  "the end": "het einde",
  "the exercise": "de oefening",
  "the flag": "de vlag",
  "the future": "toekomst",
  "the happiness": "geluk",
  "the market": "de markt",
  "the money": "het geld",
  "the moon": "maan",
  "the news": "het nieuws",
  "the newspaper": "de krant",
  "the roof": "dak",
  "the shadow / shade": "de schaduw",
  "the star": "ster",
  "the war": "de oorlog",
  "to cost": "kosten",
  "to lead": "leiden",
  "to put": "zetten",
  "to smell": "ruiken",
  "to turn": "draaien"
}
